skipper/__init__.py
skipper/cli.py
skipper_ssh_cli-0.1.2.dist-info/licenses/LICENSE
skipper_ssh_cli-0.1.2.dist-info/METADATA
skipper_ssh_cli-0.1.2.dist-info/WHEEL
skipper_ssh_cli-0.1.2.dist-info/entry_points.txt
skipper_ssh_cli-0.1.2.dist-info/top_level.txt
skipper_ssh_cli-0.1.2.dist-info/RECORD
