Metadata-Version: 2.4
Name: skipper-ssh-cli
Version: 0.1.2
Summary: Jump between servers with SSH aliases and PEMs, without touching ~/.ssh/config.
Author: Richard Pedraza
License:                     GNU GENERAL PUBLIC LICENSE
Requires-Python: >=3.10
License-File: LICENSE
Requires-Dist: typer>=0.12.3
Requires-Dist: pydantic>=2.8.2
Requires-Dist: rich>=13.7.1
Dynamic: license-file
